grid20m/__init__.py
grid20m/cli_args.py
grid20m/grid.py
grid20m/main.py
grid20m/split.py
grid20m-0.1.0.dist-info/METADATA
grid20m-0.1.0.dist-info/WHEEL
grid20m-0.1.0.dist-info/entry_points.txt
grid20m-0.1.0.dist-info/licenses/LICENSE
grid20m-0.1.0.dist-info/RECORD
