Metadata-Version: 2.3
Name: grid20m
Version: 0.1.0
Author-email: Pedro Salas <psalas@nrao.edu>
License-File: LICENSE
Requires-Python: >=3.9
Requires-Dist: dysh
Requires-Dist: gbtgridder-20m
Requires-Dist: numpy
Requires-Dist: scipy
